safe_store/__init__.py
safe_store/config.py
safe_store/depricated.py
safe_store/store.py
safe_store/core/__init__.py
safe_store/core/db.py
safe_store/core/exceptions.py
safe_store/core/models.py
safe_store/graph/__init__.py
safe_store/graph/graph_store.py
safe_store/graph/prompts/entity_fusion_prompt.md
safe_store/graph/prompts/graph_extraction_prompt.md
safe_store/graph/prompts/graph_extraction_prompt_with_ontology.md
safe_store/graph/prompts/query_parsing_prompt.md
safe_store/indexing/__init__.py
safe_store/indexing/chunking.py
safe_store/indexing/parser.py
safe_store/processing/text_cleaning.py
safe_store/processing/tokenizers.py
safe_store/search/__init__.py
safe_store/search/similarity.py
safe_store/security/__init__.py
safe_store/security/encryption.py
safe_store/utils/__init__.py
safe_store/utils/concurrency.py
safe_store/utils/json_parsing.py
safe_store/vectorization/__init__.py
safe_store/vectorization/base.py
safe_store/vectorization/manager.py
safe_store/vectorization/utils.py
safe_store/vectorization/methods/__init__.py
safe_store/vectorization/methods/cohere/__init__.py
safe_store/vectorization/methods/cohere/description.yaml
safe_store/vectorization/methods/lollms/__init__.py
safe_store/vectorization/methods/lollms/description.yaml
safe_store/vectorization/methods/ollama/__init__.py
safe_store/vectorization/methods/ollama/description.yaml
safe_store/vectorization/methods/openai/__init__.py
safe_store/vectorization/methods/openai/description.yaml
safe_store/vectorization/methods/sentense_transformer/__init__.py
safe_store/vectorization/methods/sentense_transformer/description.yaml
safe_store/vectorization/methods/tf_idf/__init__.py
safe_store/vectorization/methods/tf_idf/description.yaml
safe_store-3.3.7.dist-info/METADATA
safe_store-3.3.7.dist-info/WHEEL
safe_store-3.3.7.dist-info/licenses/LICENSE
safe_store-3.3.7.dist-info/RECORD
