Metadata-Version: 2.4
Name: safe-store
Version: 3.3.7
Summary: Simple, concurrent SQLite-based vector store optimized for local RAG pipelines, with optional encryption.
Project-URL: Homepage, https://github.com/ParisNeo/safe_store
Project-URL: Repository, https://github.com/ParisNeo/safe_store
Project-URL: Documentation, https://github.com/ParisNeo/safe_store#readme
Project-URL: Issues, https://github.com/ParisNeo/safe_store/issues
Author-email: ParisNeo <parisneo_ai@gmail.com>
License-File: LICENSE
Keywords: concurrent,database,embedding,encryption,llm,local,rag,semantic search,sqlite,vector,webui
Classifier: Development Status :: 5 - Production/Stable
Classifier: Intended Audience :: Developers
Classifier: Intended Audience :: Science/Research
Classifier: License :: OSI Approved :: Apache Software License
Classifier: Operating System :: OS Independent
Classifier: Programming Language :: Python :: 3
Classifier: Programming Language :: Python :: 3.8
Classifier: Programming Language :: Python :: 3.9
Classifier: Programming Language :: Python :: 3.10
Classifier: Programming Language :: Python :: 3.11
Classifier: Programming Language :: Python :: 3.12
Classifier: Topic :: Database
Classifier: Topic :: Scientific/Engineering :: Artificial Intelligence
Classifier: Topic :: Security :: Cryptography
Classifier: Topic :: Software Development :: Libraries :: Python Modules
Classifier: Topic :: Text Processing :: Indexing
Requires-Python: >=3.8
Requires-Dist: ascii-colors>=0.11.6
Requires-Dist: filelock>=3.9
Requires-Dist: numpy>=1.21
Requires-Dist: pipmaster>=1.0.8
Requires-Dist: sqlalchemy
Provides-Extra: all
Requires-Dist: beautifulsoup4>=4.11; extra == 'all'
Requires-Dist: cryptography>=40.0; extra == 'all'
Requires-Dist: lxml>=4.9; extra == 'all'
Requires-Dist: ollama; extra == 'all'
Requires-Dist: openai>=1.0; extra == 'all'
Requires-Dist: pypdf>=3.10; extra == 'all'
Requires-Dist: python-docx>=1.0; extra == 'all'
Requires-Dist: scikit-learn>=1.0; extra == 'all'
Requires-Dist: sentence-transformers==4.1.0; extra == 'all'
Provides-Extra: all-vectorizers
Requires-Dist: ollama; extra == 'all-vectorizers'
Requires-Dist: openai>=1.0; extra == 'all-vectorizers'
Requires-Dist: scikit-learn>=1.0; extra == 'all-vectorizers'
Requires-Dist: sentence-transformers==4.1.0; extra == 'all-vectorizers'
Provides-Extra: dev
Requires-Dist: beautifulsoup4>=4.11; extra == 'dev'
Requires-Dist: black>=22.0; extra == 'dev'
Requires-Dist: cryptography>=40.0; extra == 'dev'
Requires-Dist: flake8>=5.0; extra == 'dev'
Requires-Dist: hatchling; extra == 'dev'
Requires-Dist: lxml; extra == 'dev'
Requires-Dist: lxml>=4.9; extra == 'dev'
Requires-Dist: mypy>=0.9; extra == 'dev'
Requires-Dist: ollama; extra == 'dev'
Requires-Dist: openai>=1.0; extra == 'dev'
Requires-Dist: pypdf>=3.10; extra == 'dev'
Requires-Dist: pytest-cov>=3.0; extra == 'dev'
Requires-Dist: pytest>=7.0; extra == 'dev'
Requires-Dist: python-docx>=1.0; extra == 'dev'
Requires-Dist: scikit-learn>=1.0; extra == 'dev'
Requires-Dist: sentence-transformers==4.1.0; extra == 'dev'
Requires-Dist: sphinx-rtd-theme>=1.0; extra == 'dev'
Requires-Dist: sphinx>=5.0; extra == 'dev'
Requires-Dist: twine; extra == 'dev'
Requires-Dist: types-cryptography; extra == 'dev'
Requires-Dist: types-filelock; extra == 'dev'
Requires-Dist: wheel; extra == 'dev'
Provides-Extra: encryption
Requires-Dist: cryptography>=40.0; extra == 'encryption'
Provides-Extra: ollama
Requires-Dist: ollama; extra == 'ollama'
Provides-Extra: openai
Requires-Dist: openai>=1.0; extra == 'openai'
Provides-Extra: parsing
Requires-Dist: beautifulsoup4>=4.11; extra == 'parsing'
Requires-Dist: lxml>=4.9; extra == 'parsing'
Requires-Dist: pypdf>=3.10; extra == 'parsing'
Requires-Dist: python-docx>=1.0; extra == 'parsing'
Provides-Extra: sentence-transformers
Requires-Dist: sentence-transformers==4.1.0; extra == 'sentence-transformers'
Provides-Extra: tfidf
Requires-Dist: scikit-learn>=1.0; extra == 'tfidf'
